pygamergui/__init__.py
pygamergui/buttons.py
pygamergui/slider.py
pygamergui/text.py
pygamergui/window.py
pygamergui-0.6.dist-info/LICENSE
pygamergui-0.6.dist-info/METADATA
pygamergui-0.6.dist-info/WHEEL
pygamergui-0.6.dist-info/top_level.txt
pygamergui-0.6.dist-info/RECORD
