Metadata-Version: 2.1
Name: pygamergui
Version: 0.6
Summary: A pakage to create easy gui in Python
Home-page: https://github.com/Bishnu-coder/pygamergui
Author: vishnu01
Author-email: koharrupesh@gmail.com
Project-URL: Bug Tracker, https://github.com/Bishnu-coder/pygamergui
Classifier: Programming Language :: Python :: 3
Classifier: License :: OSI Approved :: MIT License
Classifier: Operating System :: OS Independent
Requires-Python: >=3.10
License-File: LICENSE
